permalinks/__init__.py
permalinks/admin.py
permalinks/apps.py
permalinks/models.py
permalinks/urls.py
permalinks/views.py
permalinks/middleware/__init__.py
permalinks/middleware/main.py
permalinks/migrations/0001_initial.py
permalinks/migrations/0002_auto_20190821_1759.py
permalinks/migrations/0003_auto_20200228_1938.py
permalinks/migrations/__init__.py
permalinks/templates/__init__.py
permalinks/templates/admin/__init__.py
permalinks/templates/admin/url_shortner_script.html
django_permalinks-0.1.4.dist-info/LICENSE
django_permalinks-0.1.4.dist-info/METADATA
django_permalinks-0.1.4.dist-info/WHEEL
django_permalinks-0.1.4.dist-info/top_level.txt
django_permalinks-0.1.4.dist-info/RECORD
